Metadata-Version: 2.1
Name: odoo10-addon-stock-inventory-lockdown
Version: 10.0.1.0.3
Summary: Lock down stock locations during inventories.
Home-page: https://github.com/OCA/stock-logistics-warehouse
Author: Numérigraphe, Eficent, Odoo Community Association (OCA)
Author-email: support@odoo-community.org
License: AGPL-3
Platform: UNKNOWN
Classifier: Programming Language :: Python
Classifier: Framework :: Odoo
Classifier: Framework :: Odoo :: 10.0
Classifier: License :: OSI Approved :: GNU Affero General Public License v3
Requires-Python: ~=2.7
Requires-Dist: odoo (<10.1dev,>=10.0)
